geoenrich/__init__.py
geoenrich/credentials_example.py
geoenrich/dataloader.py
geoenrich/enrichment.py
geoenrich/exports.py
geoenrich/satellite.py
geoenrich/data/AcDigitifera.zip
geoenrich/data/areas.csv
geoenrich/data/catalog.csv
geoenrich-0.6.7.dist-info/licenses/LICENSE
geoenrich-0.6.7.dist-info/METADATA
geoenrich-0.6.7.dist-info/WHEEL
geoenrich-0.6.7.dist-info/top_level.txt
geoenrich-0.6.7.dist-info/RECORD
