Metadata-Version: 2.4
Name: geoenrich
Version: 0.6.7
Summary: A package to enrich your geo-referenced data (e.g. species occurrences) with environmental data.
Author: Gaétan Morand (UMR Marbec)
Author-email: gaetan.morand@ird.fr
Project-URL: Tutorial, https://geoenrich.readthedocs.io/en/latest/tutorial.html
Project-URL: Documentation, https://geoenrich.readthedocs.io
Project-URL: Code, https://github.com/morand-g/geoenrich
Project-URL: Bug Tracker, https://github.com/morand-g/geoenrich/issues
Classifier: Programming Language :: Python :: 3
Classifier: Development Status :: 4 - Beta
Classifier: License :: OSI Approved :: GNU General Public License v3 (GPLv3)
Classifier: Operating System :: OS Independent
Classifier: Natural Language :: English
Classifier: Topic :: Software Development :: Libraries :: Python Modules
Classifier: Intended Audience :: Science/Research
Classifier: Topic :: Scientific/Engineering :: Bio-Informatics
Classifier: Topic :: Scientific/Engineering :: Atmospheric Science
Classifier: Topic :: Scientific/Engineering :: Information Analysis
Requires-Python: >=3.7
License-File: LICENSE
Requires-Dist: numpy
Requires-Dist: pandas>=2.0.0
Requires-Dist: geopandas
Requires-Dist: netCDF4
Requires-Dist: python-dwca-reader
Requires-Dist: tqdm
Requires-Dist: opencv-python
Requires-Dist: pathlib
Requires-Dist: rasterio
Requires-Dist: pygbif>=0.6.1
Requires-Dist: matplotlib
Requires-Dist: appdirs
Requires-Dist: geojson_rewind
Requires-Dist: geomet
Requires-Dist: copernicusmarine
Dynamic: license-file
